outdoorsy/__init__.py
outdoorsy/app.py
outdoorsy/database.py
outdoorsy-1.0.0.dist-info/METADATA
outdoorsy-1.0.0.dist-info/WHEEL
outdoorsy-1.0.0.dist-info/entry_points.txt
outdoorsy-1.0.0.dist-info/licenses/LICENSE
outdoorsy-1.0.0.dist-info/RECORD
