Metadata-Version: 2.1
Name: outdoorsy
Version: 1.0.0
Summary: A demo command line tool for displaying information from a comma or pipe delimited file from a fictional Company named Outdoor.sy
Project-URL: Documentation, https://github.com/rachaelcrook/outdoorsy#readme
Project-URL: Issues, https://github.com/rachaelcrook/outdoorsy/issues
Project-URL: Source, https://github.com/rachaelcrook/outdoorsy
Author-email: Rachael Crook <rachaelc@linux.com>
License: MIT License
Keywords: outdoorsy command line tool csv pipe delimited demo argparse hatchling hatch
Classifier: License :: OSI Approved :: MIT License
Classifier: Operating System :: OS Independent
Classifier: Programming Language :: Python :: 3
Requires-Python: >=3.7
Requires-Dist: colorama>=0.4.5
Requires-Dist: tabulate>=0.8.10
